{"importBase":"import","nativeBase":"native","name":"main","deps":[],"uuids":["0cdBbBSJlLhq4izw7H89h6","24xBnqY6hOoanQf8RpSJu8","7f51ojJLlGTJ8z9fJgjaR2","b3tnwWgSlMUrN2QDD6RxQO","baIUdvKGZPgZxNbjWTFuRI","d7FFnGkL1C9Jz0rSfhtUHS","e1e0UmV6JI06zJzwnzCqE4","fdjsU2o1RKF5x0TziDw3jI","ffqKYfx/ZHO4wpwcWZo6RJ","01OWf9mPBE6IGSp2YeBc25","065105f03","0b0d3b8bb","0fd467087","24xBnqY6hOoanQf8RpSJu8@6c48a","24xBnqY6hOoanQf8RpSJu8@f9941","7f51ojJLlGTJ8z9fJgjaR2@6c48a","7f51ojJLlGTJ8z9fJgjaR2@f9941","d7FFnGkL1C9Jz0rSfhtUHS@6c48a","d7FFnGkL1C9Jz0rSfhtUHS@f9941","e6zBGKnbhIepbZALTYDcwE"],"paths":{"0":["db:/assets/Scenes/game",0,1],"4":["db:/internal/physics/default-physics-material",2,1],"7":["db:/internal/default_renderpipeline/builtin-forward",1,1]},"scenes":{"db://assets/Scenes/game.scene":0},"packs":{"065105f03":[15,13,17],"0b0d3b8bb":[0,14,16,3,6,19,8],"0fd467087":[9,18]},"versions":{"import":[10,"3ca32",11,"79098",12,"78c70",1,"a2533",2,"a2533",4,"8bce7",5,"a2533",7,"731f4"],"native":[1,"841f5",2,"b15ac",3,"59751",5,"fe2c5",6,"07abd",8,"5cc3c"]},"redirect":[],"debug":false,"extensionMap":{},"hasPreloadScript":true,"dependencyRelationships":{},"types":["cc.SceneAsset","cc.RenderPipeline","cc.PhysicsMaterial"]}